<?xml version="1.0" encoding="UTF-8"?>
<feature
      id="org.pdulvp.retriever.feature"
      label="Feature"
      version="1.0.0.qualifier"
      provider-name="org.pdulvp">

   <description url="http://www.example.com/description">
      [Enter Feature Description here.]
   </description>

   <copyright url="http://www.example.com/copyright">
      [Enter Copyright Description here.]
   </copyright>

   <license url="http://www.example.com/license">
      [Enter License Description here.]
   </license>

   <requires>
      <import plugin="org.eclipse.core.runtime"/>
      <import plugin="org.eclipse.emf.ecore"/>
      <import plugin="org.eclipse.emf.ecore.xmi"/>
      <import plugin="org.eclipse.emf.edit"/>
      <import plugin="org.eclipse.emf.ecore.edit"/>
      <import plugin="org.eclipse.core.resources"/>
      <import plugin="org.eclipse.emf.edit.ui"/>
      <import plugin="org.eclipse.ui.ide"/>
      <import plugin="org.eclipse.sirius"/>
      <import plugin="org.eclipse.emf.transaction"/>
      <import plugin="com.google.gson" version="2.8.2" match="greaterOrEqual"/>
      <import plugin="org.eclipse.sirius.common"/>
      <import plugin="org.eclipse.sirius.common.acceleo.aql"/>
      <import plugin="org.apache.xerces"/>
      <import plugin="org.apache.commons.jxpath"/>
      <import plugin="org.apache.commons.codec"/>
      <import plugin="org.apache.commons.io"/>
      <import plugin="org.eclipse.sirius.ecore.extender"/>
      <import plugin="org.json"/>
      <import plugin="org.apache.batik.bridge" version="1.6.0" match="greaterOrEqual"/>
      <import plugin="org.apache.batik.transcoder" version="1.6.0" match="greaterOrEqual"/>
      <import plugin="org.htmlcleaner" version="2.1.6" match="greaterOrEqual"/>
      <import plugin="org.eclipse.ui"/>
      <import plugin="org.eclipse.ui.forms"/>
      <import plugin="org.eclipse.sirius.ui"/>
      <import plugin="org.eclipse.core.expressions"/>
      <import plugin="org.eclipse.e4.core.commands"/>
   </requires>

   <plugin
         id="org.pdulvp.retriever"
         download-size="0"
         install-size="0"
         version="0.0.0"
         unpack="false"/>

   <plugin
         id="org.pdulvp.retriever.edit"
         download-size="0"
         install-size="0"
         version="0.0.0"
         unpack="false"/>

   <plugin
         id="org.pdulvp.retriever.editor"
         download-size="0"
         install-size="0"
         version="0.0.0"
         unpack="false"/>

   <plugin
         id="org.pdulvp.retriever.model.handler"
         download-size="0"
         install-size="0"
         version="0.0.0"
         unpack="false"/>

   <plugin
         id="org.htmlcleaner"
         download-size="0"
         install-size="0"
         version="0.0.0"
         unpack="false"/>

   <plugin
         id="org.pdulvp.retriever.ui"
         download-size="0"
         install-size="0"
         version="0.0.0"
         unpack="false"/>

</feature>
